MANIFEST.in
Makefile
README
babyGPT-1.1.3.html
setup.py
Examples/112_babygpt_tokenizer_50002.json
Examples/112_babygpt_tokenizer_cl_35035.json
Examples/README
Examples/apply_tokenizer.py
Examples/create_base_model_with_buffered_context.py
Examples/extend_previously_trained_tokenizer.py
Examples/interact_with_prompts.py
Examples/run_gatherer.py
Examples/text_sample_for_testing.txt
Examples/total_chars.sh
Examples/train_tokenizer.py
TestBabyGPT/Test.py
TestBabyGPT/TestDecoderInstall.py
TestBabyGPT/babyGPT.py
babyGPT/__init__.py
babyGPT/babyGPT.py
babyGPT.egg-info/PKG-INFO
babyGPT.egg-info/SOURCES.txt
babyGPT.egg-info/dependency_links.txt
babyGPT.egg-info/top_level.txt