Metadata-Version: 2.1
Name: babyGPT
Version: 1.1.3
Summary: An educational module for experimenting with unsupervised learning in large language modeling
Home-page: https://engineering.purdue.edu/kak/distBabyGPT/babyGPT-1.1.3.html
Download-URL: https://engineering.purdue.edu/kak/distBabyGPT/babyGPT-1.1.3.tar.gz
Author: Avinash Kak
Author-email: kak@purdue.edu
Maintainer: Avinash Kak
Maintainer-email: kak@purdue.edu
License: Python Software Foundation License
Keywords: language modeling,unsupervised learning
Platform: All platforms
Classifier: Topic :: Scientific/Engineering :: Artificial Intelligence
Classifier: Programming Language :: Python :: 3.10
